{
  "articles": [
    {
      "title": "第三者アプリストア構築の技術アーキテクチャ完全ガイド",
      "subtitle": "Flutter、Next.js、NestJSを活用した実装レベルの詳細解説",
      "slug": "third-party-app-store-architecture-guide",
      "category": "tech_deep_dive",
      "tags": ["アプリストア", "Flutter", "NestJS", "Next.js", "アーキテクチャ", "TypeScript", "AWS", "CDN", "マイクロサービス"],
      "excerpt": "2025年12月の日本のスマホ新法施行に向けて、独自のアプリストアを構築するための技術アーキテクチャを実装レベルで詳しく解説します。配信システム、セキュリティ、スケーラビリティなど、実践的なコード例を交えて紹介。",
      "is_featured": true,
      "is_premium": false,
      "cover_image_keywords": "mobile app development architecture",
      "reading_time": 15
    },
    {
      "title": "第三者アプリストアのセキュリティ実装完全ガイド：脅威対策から実装まで",
      "subtitle": "マルウェア対策、KYC、ゼロトラストアーキテクチャの実装方法",
      "slug": "app-store-security-implementation-guide",
      "category": "tech_deep_dive",
      "tags": ["セキュリティ", "マルウェア対策", "KYC", "ゼロトラスト", "サンドボックス", "静的解析", "動的解析", "OWASP"],
      "excerpt": "第三者アプリストアを運営する上で最重要となるセキュリティ対策を、実装レベルで解説。静的・動的解析、KYCシステム、ゼロトラストアーキテクチャなど、実践的なTypeScriptコードとともに紹介します。",
      "is_featured": true,
      "is_premium": false,
      "cover_image_keywords": "cybersecurity mobile app protection",
      "reading_time": 18
    }
  ],
  "instructions": "管理画面（http://localhost:3001/admin/articles/new）から記事を作成してください。内容はtech-articlesフォルダ内のMarkdownファイルをコピーして使用してください。"
}